vllm_launcher/__init__.py
vllm_launcher/simple.py
vllm_marenostrum-1.0.2.dist-info/licenses/LICENSE
vllm_marenostrum-1.0.2.dist-info/METADATA
vllm_marenostrum-1.0.2.dist-info/WHEEL
vllm_marenostrum-1.0.2.dist-info/entry_points.txt
vllm_marenostrum-1.0.2.dist-info/top_level.txt
vllm_marenostrum-1.0.2.dist-info/RECORD
