Metadata-Version: 2.4
Name: vllm-marenostrum
Version: 1.0.2
Summary: Super simple vLLM server launcher for SLURM/HPC with nested config support
Author-email: Olivier Philippe <olivier.philippe@gmail.com>
Project-URL: Homepage, https://gitlab.bsc.es/social-link-analytic/vllm_marenostrum
Requires-Python: >=3.12
License-File: LICENSE
Requires-Dist: PyYAML
Requires-Dist: vllm
Requires-Dist: requests
Dynamic: license-file
